<annotation>
    <folder>images</folder>
    <filename>1380.jpg</filename>
    <size>
        <width>640</width>
        <height>480</height>
        <depth>3</depth>
    </size>
    <object>
        <name>zang_wu</name>
        <pose>Unspecified</pose>
        <truncated>0</truncated>
        <difficult>0</difficult>
        <bndbox>
            <xmin>236</xmin>
            <ymin>127</ymin>
            <xmax>303</xmax>
            <ymax>218</ymax>
        </bndbox>
    </object>
    <object>
        <name>zang_wu</name>
        <pose>Unspecified</pose>
        <truncated>0</truncated>
        <difficult>0</difficult>
        <bndbox>
            <xmin>363</xmin>
            <ymin>220</ymin>
            <xmax>456</xmax>
            <ymax>303</ymax>
        </bndbox>
    </object>
    <object>
        <name>zhen_kong</name>
        <pose>Unspecified</pose>
        <truncated>0</truncated>
        <difficult>0</difficult>
        <bndbox>
            <xmin>300</xmin>
            <ymin>230</ymin>
            <xmax>337</xmax>
            <ymax>264</ymax>
        </bndbox>
    </object>
    <object>
        <name>zhen_kong</name>
        <pose>Unspecified</pose>
        <truncated>0</truncated>
        <difficult>0</difficult>
        <bndbox>
            <xmin>368</xmin>
            <ymin>328</ymin>
            <xmax>408</xmax>
            <ymax>369</ymax>
        </bndbox>
    </object>
    <object>
        <name>ca_shang</name>
        <pose>Unspecified</pose>
        <truncated>0</truncated>
        <difficult>0</difficult>
        <bndbox>
            <xmin>162</xmin>
            <ymin>280</ymin>
            <xmax>346</xmax>
            <ymax>386</ymax>
        </bndbox>
    </object>
</annotation>